{
"type": "FeatureCollection",
"name": "KJFK_all.windsocks",
"crs": { "type": "name", "properties": { "name": "urn:ogc:def:crs:OGC:1.3:CRS84" } },
"features": [
{ "type": "Feature", "properties": { "illuminated": true, "name": "WS - 4R" }, "geometry": { "type": "Point", "coordinates": [ -73.77371585, 40.62760369 ] } },
{ "type": "Feature", "properties": { "illuminated": true, "name": "WS - 22L" }, "geometry": { "type": "Point", "coordinates": [ -73.76040584, 40.64130803 ] } },
{ "type": "Feature", "properties": { "illuminated": true, "name": "WS - 31L" }, "geometry": { "type": "Point", "coordinates": [ -73.78398141, 40.63267066 ] } },
{ "type": "Feature", "properties": { "illuminated": true, "name": "WS - 13R" }, "geometry": { "type": "Point", "coordinates": [ -73.81531495, 40.64901164 ] } },
{ "type": "Feature", "properties": { "illuminated": false, "name": "WS - 31R" }, "geometry": { "type": "Point", "coordinates": [ -73.76482001, 40.64709963 ] } }
]
}
